{
    "$schema": "https://schemas.wp.org/trunk/theme.json",
    "version": 2,
    "settings": {
        "appearanceTools": true,
        "layout": {
            "contentSize": "800px",
            "wideSize": "1200px"
        },
        "color": {
            "defaultPalette": false,
            "palette": [
                {
                    "name": "Primary",
                    "slug": "primary",
                    "color": "#E63946"
                },
                {
                    "name": "Secondary",
                    "slug": "secondary",
                    "color": "#374151"
                },
                {
                    "name": "Base",
                    "slug": "base",
                    "color": "#ffffff"
                },
                {
                    "name": "Contrast",
                    "slug": "contrast",
                    "color": "#000000"
                },
                {
                    "slug": "brand-primary",
                    "name": "Brand Primary",
                    "color": "#E63946"
                }
            ]
        },
        "typography": {
            "fontSizes": [
                {
                    "name": "Small",
                    "slug": "small",
                    "size": "0.875rem"
                },
                {
                    "name": "Medium",
                    "slug": "medium",
                    "size": "1rem"
                },
                {
                    "name": "Large",
                    "slug": "large",
                    "size": "1.5rem"
                },
                {
                    "name": "Extra Large",
                    "slug": "x-large",
                    "size": "2.25rem"
                }
            ]
        }
    },
    "styles": {
        "typography": {
            "fontFamily": "system-ui, -apple-system, sans-serif",
            "fontSize": "1rem",
            "lineHeight": "1.6"
        },
        "blocks": {
            "core/post-title": {
                "typography": {
                    "fontWeight": "700"
                }
            }
        }
    },
    "templateParts": [
        {
            "name": "header",
            "title": "Header",
            "area": "header"
        },
        {
            "name": "footer",
            "title": "Footer",
            "area": "footer"
        }
    ]
}
